Workbook

Sheet Реєстр
A1: Зведений реєстр дефектів вимог SRS v1.0 «ФінКит»
A2: Команда: BMIBM-banking | Зведення: Тест-аналітик (Пономаренко Р. В.) | Джерела: аркуші аудиту Мажуги І. К., Пономаренка Р. В., Городиської А. А.
A4: =COUNTIF(G8:G29,"<>Відхилено після обговорення") -> 21 | C4: =SUMPRODUCT(--(COUNTIFS(C8:C29,{"Однозначність","Повнота","Несуперечливість","Простежуваність","Здійсненність","Тестопридатність"},G8:G29,"<>Відхилено після обговорення")>0))&" / 6" -> 6 / 6 | E4: 27 записів у 3 аркушах → 22 унікальних (вилучено дублікатів: 5)
A5: ДЕФЕКТІВ У РЕЄСТРІ (БЕЗ ВІДХИЛЕНИХ) | C5: КРИТЕРІЇВ ЯКОСТІ ПОКРИТО | E5: ВИЛУЧЕННЯ ДУБЛІКАТІВ
A7: № | B7: ID вимоги | C7: Критерій якості | D7: Опис дефекту (цитата вимоги + порушення чек-листа) | E7: Пропозиція виправлення | F7: Хто знайшов | G7: Статус | H7: Розділ SRS | I7: Джерела (аркуші)
A8: 1 | B8: F-50 | C8: Повнота | D8: Цитата: «Склад полів переліку операцій визначено в документі «Регламент виписок ФК-РВ-2»». Порушення (п. 3): Посилання на неіснуючий документ. У розділі 1.4 «Посилання» зазначено лише Каталог продуктів, README модуля бізнес-логіки та demo ParaBank; документ «Регламент виписок ФК-РВ-2» відсутній у специфікації та додатках. | E8: «Перелік операцій сторінки «Деталі рахунку» відображає таблицю з обов'язковими полями: дата операції (ДД.ММ.РРРР), тип операції (зарахування/списання), опис/призначення, сума у гривнях та залишок коштів після проведення операції.» | F8: Мажуга І. К. | G8: Прийнято | H8: F | I8: Лід №3
A9: 2 | B9: F-70 / BL-40 | C9: Несуперечливість | D9: Цитата у F-70: «Загальна сума переказів клієнта за одну добу не може перевищувати 100 000 грн». Порушення (п. 2): Вимога F-70 суперечить правилу бізнес-логіки модуля BL-40, де вказано: «todaySpent + amount ≤ 50 000 грн (денний ліміт)». Функціональна вимога дозволяє ліміт до 100 000 грн, тоді як модуль відхиляє операції понад 50 000 грн кодом DAILY_LIMIT_EXCEEDED. | E9: Узгодити F-70 з правилом модуля BL-40: «Загальна сума переказів клієнта за одну календарну добу між власними рахунками не може перевищувати 50 000.00 грн (відповідно до правила модуля BL-40); при спробі перевищення операція блокується з повідомленням про ліміт». | F9: Мажуга І. К. | G9: Прийнято | H9: F; BL | I9: Лід №2
A10: 3 | B10: F-80 | C10: Здійсненність | D10: Цитата: «Перед відправленням система перевіряє наявність одержувача в реєстрах усіх банків світу та його платоспроможність, після чого списує суму…». Порушення (п. 1): Вимога технічно та юридично нездійсненна. Єдиного реєстру банків і рахунків «усього світу» не існує, а платоспроможність фізичної особи — конфіденційні дані, до яких вебзастосунок доступу не має. Реалізувати і перевірити таку вимогу неможливо. | E10: «Перед відправленням система перевіряє, що номер рахунку одержувача відповідає формату BL-50 і збігається з полем «Підтвердження номера рахунку», що він не збігається з рахунком списання, а сума не перевищує доступну суму рахунку. Перевірка в зовнішніх реєстрах не виконується.» | F10: Пономаренко Р. В. | G10: Прийнято | H10: F | I10: Аналітик №1
A11: 4 | B11: F-90 | C11: Однозначність | D11: Цитата: «Клієнт обирає рахунок та один із критеріїв пошуку... Дати вводяться у стандартному форматі». Порушення (п. 1, 4): Термін «стандартний формат» не визначено і він допускає суперечливі інтерпретації (ДД.ММ.РРРР, РРРР-ММ-ДД або ММ/ДД/РРРР). Відсутність єдиного формату унеможливлює однозначну перевірку та реалізацію валідації полів пошуку. | E11: «Поля вибору дат приймають значення виключно у форматі ДД.ММ.РРРР через інтерактивний календарний віджет або прямим введенням із маскою; при введенні неіснуючої дати виводиться повідомлення «Введіть коректну дату у форматі ДД.ММ.РРРР».» | F11: Мажуга І. К. | G11: Прийнято | H11: F | I11: Лід №5
A12: 5 | B12: F-110 | C12: Повнота | D12: Цитата: «Клієнт вводить суму кредиту та перший внесок, обирає рахунок для списання внеску і подає заявку. Система показує рішення… «Схвалено»… або «Відхилено» з поясненням причини». Порушення (п. 3): Для обчислення платежу за BL-10 потрібні строк n і ставка r, але у формі їх немає. Не визначено правила рішення та перелік причин відмови (п. 2.3.5 виносить параметри за межі документа), а також реакцію на недостатню суму для першого внеску. | E12: Додати у форму поля «Строк, міс.» (3..60) і «Річна ставка, %» (5..40); виводити щомісячний платіж за BL-10. Визначити закритий перелік причин відмови (напр., «Недостатньо коштів для першого внеску», «Не пройдено поріг кредитного рішення») і правило схвалення з параметрами адміністратора. | F12: Пономаренко Р. В. | G12: Прийнято | H12: F | I12: Аналітик №5
A13: 6 | B13: F-110 / BL-30 | C13: Несуперечливість | D13: Цитата F-110: «Мінімальна сума кредиту — 500 грн». Цитата BL-30: «…приймають лише P у межах 1 000..1 000 000 грн… для будь-якого значення поза межами метод кидає IllegalArgumentException». Порушення (п. 2): Заявка на суму 500–999 грн дозволена за F-110, але модуль відхилить її винятком. Мінімальні межі суми кредиту не збігаються. | E13: Узгодити F-110 з BL-30: «Сума кредиту — від 1 000 до 1 000 000 грн (включно). За суми поза цим діапазоном система показує повідомлення «Сума кредиту має бути від 1 000 до 1 000 000 грн» і заявку не подає.» (яку межу вважати правильною — див. аркуш «Спірні»). | F13: Пономаренко Р. В. | G13: Прийнято | H13: F; BL | I13: Аналітик №3
A14: 7 | B14: F-130 / F-140 | C14: Простежуваність | D14: Цитата F-130: «Сторінка «Служба підтримки» містить форму з полями ім'я, e-mail, телефон, повідомлення та кнопку «Надіслати»...» Цитата F-140: «Відвідувач може надіслати звернення до служби підтримки через форму зворотного зв'язку, вказавши ім'я, е-mail, телефон і текст звернення...» Порушення (п. 1, 5): Дублювання та перетин функціональності під двома різними ID. Однакова функція форми зворотного зв'язку описана двічі різними словами. | E14: Залишити детальне формулювання у вимозі F-130: «Клієнт або відвідувач надсилає звернення до служби підтримки через форму з полями: ім'я, e-mail, телефон, повідомлення...». Вимогу F-140 вилучити з тексту специфікації із фіксацією в журналі змін (без зсуву інших ID). | F14: Мажуга І. К. | G14: Прийнято | H14: F | I14: Лід №6
A15: 8 | B15: GUI-40 | C15: Простежуваність | D15: Цитата: GUI-40 — «Після входу ліва колонка містить привітання «Вітаємо, <Ім'я Прізвище>» і меню кабінету…» та GUI-40 — «Форма відкриття рахунку містить список «Тип рахунку»…». Порушення (п. 1): Один ідентифікатор присвоєно двом різним вимогам. Посилання на GUI-40 у тест-кейсах і матриці простежуваності неоднозначне. | E15: Залишити GUI-40 за вимогою про меню кабінету, а форму відкриття рахунку позначити GUI-45 (проміжний ID, без перенумерації інших вимог) із записом у журналі змін. | F15: Пономаренко Р. В. | G15: Прийнято | H15: GUI | I15: Аналітик №4
A16: 9 | B16: GUI-50 | C16: Однозначність | D16: Цитата: «Якщо суму у формі переказу або оплати рахунку введено некоректно, система показує відповідне повідомлення помітним кольором». Порушення (п. 1, 4): Не визначено, що вважається «некоректною» сумою, текст «відповідного повідомлення» та колір («помітним»). Різні виконавці й тестувальники трактуватимуть вимогу по-різному. | E16: «Якщо сума порожня, не є числом, не більша за 0 або має понад 2 знаки після коми, під полем «Сума» червоним кольором (#FF0000) показується повідомлення «Введіть коректну суму, більшу за 0».» | F16: Пономаренко Р. В.; Городиська А. А. | G16: Прийнято | H16: GUI | I16: Аналітик №7; Інженер №2
A17: 10 | B17: GUI-70 | C17: Тестопридатність | D17: Цитата: «Форма заявки на кредит має бути інтуїтивно зрозумілою для клієнта». Порушення: Фраза «інтуїтивно зрозуміла» суб'єктивна й не дає вимірюваного критерію: результат перевірки неможливо однозначно визначити як «пройдено / не пройдено». | E17: «Клієнт заповнює форму заявки на кредит (поля за F-110) з першої спроби, без використання довідки, не довше ніж за 2 хвилини.» | F17: Городиська А. А. | G17: Прийнято | H17: GUI | I17: Інженер №3
A18: 11 | B18: Розд. 4: між GUI-70 і GUI-80 (без ID) | C18: Простежуваність | D18: Цитата: «Повідомлення про помилки введення показуються червоним кольором поряд із полем, якого стосуються». Порушення: Вимога не має власного унікального ідентифікатора, тому на неї неможливо послатися в тест-кейсі та матриці простежуваності (вимога без ID — сама по собі дефект простежуваності). Також перетинається з GUI-50 і U-20. | E18: Присвоїти вільний ID GUI-75 (проміжний, без перенумерації інших вимог) і додати посилання на U-20; зміну зафіксувати в журналі змін. | F18: Городиська А. А. | G18: Прийнято | H18: GUI | I18: Інженер №1
A19: 12 | B19: S-10 / GUI-80 | C19: Несуперечливість | D19: Цитата S-10: «Сеанс клієнта автоматично завершується після 15 хвилин бездіяльності; для продовження роботи потрібен повторний вхід». Порушення (п. 2): Пряма суперечність із вимогою GUI-80: «Після входу сеанс клієнта залишається активним протягом 8 годин незалежно від активності; повторний вхід протягом цього часу не потрібен». Обидві вимоги описують тайм-аут сесії з протилежною логікою. | E19: Узгодити політику сесій: «Сеанс клієнта автоматично завершується після 15 хвилин бездіяльності (відповідно до S-10). При цьому максимальна загальна тривалість безперервної сесії навіть за умови постійної активності становить не більше 8 годин, після чого вимагається повторна автентифікація (зміна до GUI-80).» | F19: Мажуга І. К.; Городиська А. А. | G19: Прийнято | H19: GUI; S | I19: Лід №4; Інженер №4
... A29: 22 | B29: D-20 | C29: Повнота | D29: Цитата: «Інструкція адміністратора описує процедуру скидання даних (F-150) та налаштування параметрів кредитного рішення (F-160)». Порушення: Посилання на F-150 і F-160, проте в розділі 3 вимог з такими ID немає (останній — F-140). | E29: Додати у розділ 3 нові вимоги (існуючі ID не зсувати): F-150 — адміністратор ініціалізує й очищає дані застосунку; F-160 — адміністратор задає параметри кредитного рішення (спосіб опрацювання заявки, поріг у %). Це також закриває прогалину п. 2.3.5 і F-110. | F29: Городиська А. А. | G29: Прийнято | H29: D | I29: Інженер №10

Sheet Розподіл розділів
A1: Розподіл розділів SRS між аудиторами та перевірка покриття
A2: Правило: кожен розділ мають перевірити щонайменше двоє учасників. «Закріплено» — за планом спринту; «Знахідок» — записи реєстру (з відхиленими), що стосуються розділу.
A4: Розділ | B4: Склад розділу | C4: Закріплено за планом (✓) | F4: Знахідок у реєстрі | I4: Аудиторів (план або знахідки) | J4: Дефектів у реєстрі (без відхилених) | K4: Покриття ≥ 2 аудиторів
C5: Мажуга І. К. | D5: Пономаренко Р. В. | E5: Городиська А. А. | F5: Мажуга І. К. | G5: Пономаренко Р. В. | H5: Городиська А. А.
A6: 1–2 | B6: 1. Вступ; 2. Загальний опис (ролі, середовище, обмеження) | C6: ✓ | D6: — | E6: — | F6: =SUMPRODUCT(ISNUMBER(SEARCH("; "&$A6&";","; "&Реєстр!$H$8:$H$29&";"))*ISNUMBER(SEARCH(C$5,Реєстр!$F$8:$F$29))) -> 0 | G6: =SUMPRODUCT(ISNUMBER(SEARCH("; "&$A6&";","; "&Реєстр!$H$8:$H$29&";"))*ISNUMBER(SEARCH(D$5,Реєстр!$F$8:$F$29))) -> 0 | H6: =SUMPRODUCT(ISNUMBER(SEARCH("; "&$A6&";","; "&Реєстр!$H$8:$H$29&";"))*ISNUMBER(SEARCH(E$5,Реєстр!$F$8:$F$29))) -> 0 | I6: =SUMPRODUCT(--(((C6:E6="✓")+(F6:H6>0))>0)) -> 1 | J6: =SUMPRODUCT(ISNUMBER(SEARCH("; "&$A6&";","; "&Реєстр!$H$8:$H$29&";"))*(Реєстр!$G$8:$G$29<>"Відхилено після обговорення")) -> 0 | K6: =IF(I6>=2,"так","ні — потрібна друга вичитка") -> ні — потрібна друга вичитка
A7: F | B7: 3. Функціональні вимоги F-10…F-140 | C7: ✓ | D7: ✓ | E7: — | F7: =SUMPRODUCT(ISNUMBER(SEARCH("; "&$A7&";","; "&Реєстр!$H$8:$H$29&";"))*ISNUMBER(SEARCH(C$5,Реєстр!$F$8:$F$29))) -> 4 | G7: =SUMPRODUCT(ISNUMBER(SEARCH("; "&$A7&";","; "&Реєстр!$H$8:$H$29&";"))*ISNUMBER(SEARCH(D$5,Реєстр!$F$8:$F$29))) -> 3 | H7: =SUMPRODUCT(ISNUMBER(SEARCH("; "&$A7&";","; "&Реєстр!$H$8:$H$29&";"))*ISNUMBER(SEARCH(E$5,Реєстр!$F$8:$F$29))) -> 0 | I7: =SUMPRODUCT(--(((C7:E7="✓")+(F7:H7>0))>0)) -> 2 | J7: =SUMPRODUCT(ISNUMBER(SEARCH("; "&$A7&";","; "&Реєстр!$H$8:$H$29&";"))*(Реєстр!$G$8:$G$29<>"Відхилено після обговорення")) -> 7 | K7: =IF(I7>=2,"так","ні — потрібна друга вичитка") -> так
A8: GUI | B8: 4. Вимоги до інтерфейсу GUI-10…GUI-80 | C8: — | D8: ✓ | E8: ✓ | F8: =SUMPRODUCT(ISNUMBER(SEARCH("; "&$A8&";","; "&Реєстр!$H$8:$H$29&";"))*ISNUMBER(SEARCH(C$5,Реєстр!$F$8:$F$29))) -> 1 | G8: =SUMPRODUCT(ISNUMBER(SEARCH("; "&$A8&";","; "&Реєстр!$H$8:$H$29&";"))*ISNUMBER(SEARCH(D$5,Реєстр!$F$8:$F$29))) -> 2 | H8: =SUMPRODUCT(ISNUMBER(SEARCH("; "&$A8&";","; "&Реєстр!$H$8:$H$29&";"))*ISNUMBER(SEARCH(E$5,Реєстр!$F$8:$F$29))) -> 4 | I8: =SUMPRODUCT(--(((C8:E8="✓")+(F8:H8>0))>0)) -> 3 | J8: =SUMPRODUCT(ISNUMBER(SEARCH("; "&$A8&";","; "&Реєстр!$H$8:$H$29&";"))*(Реєстр!$G$8:$G$29<>"Відхилено після обговорення")) -> 5 | K8: =IF(I8>=2,"так","ні — потрібна друга вичитка") -> так
A9: BL | B9: 5. Вимоги до бізнес-логіки модуля BL-10…BL-80 | C9: — | D9: ✓ | E9: ✓ | F9: =SUMPRODUCT(ISNUMBER(SEARCH("; "&$A9&";","; "&Реєстр!$H$8:$H$29&";"))*ISNUMBER(SEARCH(C$5,Реєстр!$F$8:$F$29))) -> 1 | G9: =SUMPRODUCT(ISNUMBER(SEARCH("; "&$A9&";","; "&Реєстр!$H$8:$H$29&";"))*ISNUMBER(SEARCH(D$5,Реєстр!$F$8:$F$29))) -> 4 | H9: =SUMPRODUCT(ISNUMBER(SEARCH("; "&$A9&";","; "&Реєстр!$H$8:$H$29&";"))*ISNUMBER(SEARCH(E$5,Реєстр!$F$8:$F$29))) -> 3 | I9: =SUMPRODUCT(--(((C9:E9="✓")+(F9:H9>0))>0)) -> 3 | J9: =SUMPRODUCT(ISNUMBER(SEARCH("; "&$A9&";","; "&Реєстр!$H$8:$H$29&";"))*(Реєстр!$G$8:$G$29<>"Відхилено після обговорення")) -> 5 | K9: =IF(I9>=2,"так","ні — потрібна друга вичитка") -> так
A10: P | B10: 6. Нефункціональні: продуктивність P-10, P-20 | C10: ✓ | D10: — | E10: — | F10: =SUMPRODUCT(ISNUMBER(SEARCH("; "&$A10&";","; "&Реєстр!$H$8:$H$29&";"))*ISNUMBER(SEARCH(C$5,Реєстр!$F$8:$F$29))) -> 2 | G10: =SUMPRODUCT(ISNUMBER(SEARCH("; "&$A10&";","; "&Реєстр!$H$8:$H$29&";"))*ISNUMBER(SEARCH(D$5,Реєстр!$F$8:$F$29))) -> 0 | H10: =SUMPRODUCT(ISNUMBER(SEARCH("; "&$A10&";","; "&Реєстр!$H$8:$H$29&";"))*ISNUMBER(SEARCH(E$5,Реєстр!$F$8:$F$29))) -> 0 | I10: =SUMPRODUCT(--(((C10:E10="✓")+(F10:H10>0))>0)) -> 1 | J10: =SUMPRODUCT(ISNUMBER(SEARCH("; "&$A10&";","; "&Реєстр!$H$8:$H$29&";"))*(Реєстр!$G$8:$G$29<>"Відхилено після обговорення")) -> 2 | K10: =IF(I10>=2,"так","ні — потрібна друга вичитка") -> ні — потрібна друга вичитка
A11: S | B11: 6. Нефункціональні: безпека S-10, S-20 | C11: ✓ | D11: — | E11: — | F11: =SUMPRODUCT(ISNUMBER(SEARCH("; "&$A11&";","; "&Реєстр!$H$8:$H$29&";"))*ISNUMBER(SEARCH(C$5,Реєстр!$F$8:$F$29))) -> 2 | G11: =SUMPRODUCT(ISNUMBER(SEARCH("; "&$A11&";","; "&Реєстр!$H$8:$H$29&";"))*ISNUMBER(SEARCH(D$5,Реєстр!$F$8:$F$29))) -> 0 | H11: =SUMPRODUCT(ISNUMBER(SEARCH("; "&$A11&";","; "&Реєстр!$H$8:$H$29&";"))*ISNUMBER(SEARCH(E$5,Реєстр!$F$8:$F$29))) -> 2 | I11: =SUMPRODUCT(--(((C11:E11="✓")+(F11:H11>0))>0)) -> 2 | J11: =SUMPRODUCT(ISNUMBER(SEARCH("; "&$A11&";","; "&Реєстр!$H$8:$H$29&";"))*(Реєстр!$G$8:$G$29<>"Відхилено після обговорення")) -> 2 | K11: =IF(I11>=2,"так","ні — потрібна друга вичитка") -> так
A12: U | B12: 6. Нефункціональні: зручність U-10, U-20 | C12: — | D12: — | E12: ✓ | F12: =SUMPRODUCT(ISNUMBER(SEARCH("; "&$A12&";","; "&Реєстр!$H$8:$H$29&";"))*ISNUMBER(SEARCH(C$5,Реєстр!$F$8:$F$29))) -> 0 | G12: =SUMPRODUCT(ISNUMBER(SEARCH("; "&$A12&";","; "&Реєстр!$H$8:$H$29&";"))*ISNUMBER(SEARCH(D$5,Реєстр!$F$8:$F$29))) -> 0 | H12: =SUMPRODUCT(ISNUMBER(SEARCH("; "&$A12&";","; "&Реєстр!$H$8:$H$29&";"))*ISNUMBER(SEARCH(E$5,Реєстр!$F$8:$F$29))) -> 1 | I12: =SUMPRODUCT(--(((C12:E12="✓")+(F12:H12>0))>0)) -> 1 | J12: =SUMPRODUCT(ISNUMBER(SEARCH("; "&$A12&";","; "&Реєстр!$H$8:$H$29&";"))*(Реєстр!$G$8:$G$29<>"Відхилено після обговорення")) -> 1 | K12: =IF(I12>=2,"так","ні — потрібна друга вичитка") -> ні — потрібна друга вичитка
A13: D | B13: 6. Нефункціональні: документація D-10, D-20 | C13: — | D13: — | E13: ✓ | F13: =SUMPRODUCT(ISNUMBER(SEARCH("; "&$A13&";","; "&Реєстр!$H$8:$H$29&";"))*ISNUMBER(SEARCH(C$5,Реєстр!$F$8:$F$29))) -> 0 | G13: =SUMPRODUCT(ISNUMBER(SEARCH("; "&$A13&";","; "&Реєстр!$H$8:$H$29&";"))*ISNUMBER(SEARCH(D$5,Реєстр!$F$8:$F$29))) -> 0 | H13: =SUMPRODUCT(ISNUMBER(SEARCH("; "&$A13&";","; "&Реєстр!$H$8:$H$29&";"))*ISNUMBER(SEARCH(E$5,Реєстр!$F$8:$F$29))) -> 2 | I13: =SUMPRODUCT(--(((C13:E13="✓")+(F13:H13>0))>0)) -> 1 | J13: =SUMPRODUCT(ISNUMBER(SEARCH("; "&$A13&";","; "&Реєстр!$H$8:$H$29&";"))*(Реєстр!$G$8:$G$29<>"Відхилено після обговорення")) -> 2 | K13: =IF(I13>=2,"так","ні — потрібна друга вичитка") -> ні — потрібна друга вичитка
A15: Примітки до покриття
A16: 1. Розділи 1–2, P, U, D за наявними аркушами перевірив лише один учасник. Для виконання правила «двоє на розділ» потрібна додаткова вичитка (наприклад, на сесії зведення — коротким проходом другого учасника).
A17: 2. Розділ S зараховано як покритий двома учасниками за знахідками (Мажуга — S-10, S-20; Городиська — S-10 у суперечності з GUI-80 і S-20), хоча за планом він закріплений лише за Мажугою.
A18: 3. Дефект, що стосується двох розділів (напр., F-70 / BL-40), враховано в обох розділах, тому сума по розділах може перевищувати загальну кількість дефектів.
A20: Покриття критеріїв якості (норматив: ≥ 2 на кожен критерій, ≥ 12 усього)
B21: Критерій якості | C21: Знайдено | D21: Норматив | E21: Виконано
B22: Однозначність | C22: =COUNTIFS(Реєстр!$C$8:$C$29,B22,Реєстр!$G$8:$G$29,"<>Відхилено після обговорення") -> 2 | D22: 2 | E22: =IF(C22>=D22,"так","ні") -> так
B23: Повнота | C23: =COUNTIFS(Реєстр!$C$8:$C$29,B23,Реєстр!$G$8:$G$29,"<>Відхилено після обговорення") -> 4 | D23: 2 | E23: =IF(C23>=D23,"так","ні") -> так
B24: Несуперечливість | C24: =COUNTIFS(Реєстр!$C$8:$C$29,B24,Реєстр!$G$8:$G$29,"<>Відхилено після обговорення") -> 3 | D24: 2 | E24: =IF(C24>=D24,"так","ні") -> так
B25: Простежуваність | C25: =COUNTIFS(Реєстр!$C$8:$C$29,B25,Реєстр!$G$8:$G$29,"<>Відхилено після обговорення") -> 3 | D25: 2 | E25: =IF(C25>=D25,"так","ні") -> так
B26: Здійсненність | C26: =COUNTIFS(Реєстр!$C$8:$C$29,B26,Реєстр!$G$8:$G$29,"<>Відхилено після обговорення") -> 3 | D26: 2 | E26: =IF(C26>=D26,"так","ні") -> так
B27: Тестопридатність | C27: =COUNTIFS(Реєстр!$C$8:$C$29,B27,Реєстр!$G$8:$G$29,"<>Відхилено після обговорення") -> 6 | D27: 2 | E27: =IF(C27>=D27,"так","ні") -> так
B28: Разом | C28: =SUM(C22:C27) -> 21 | D28: 12 | E28: =IF(C28>=D28,"так","ні") -> так

Sheet Спірні
A1: Спірні записи реєстру дефектів вимог
A2: Для модерації (роль «адвокат замовника»): розбіжності в авторів, класифікації та способі виправлення. Рекомендації — пропозиція до обговорення, остаточне рішення — за командою.
A4: № | B4: Реєстр №; ID вимоги | C4: Суть розбіжності | D4: Позиція 1 | E4: Позиція 2 | F4: Аргументація (за текстом SRS і чек-листом) | G4: Рекомендоване рішення | H4: Статус
A5: 1 | B5: №13 BL-40 | C5: Чи є дефект повноти: BL-40 «не описує реакцію на невалідні суми». | D5: Городиська А. А.: додати «Якщо amount ≤ 0, повертається код AMOUNT_NOT_POSITIVE». | E5: Контрпозиція (перевірка за текстом): запис не підтверджується. | F5: BL-40 уже вимагає «amount > 0» і прямо називає код AMOUNT_NOT_POSITIVE у переліку кодів порушень. Запропонований текст дублює наявну вимогу, тобто порушення повноти немає. | G5: Відхилити запис. Залишити його в реєстрі зі статусом «Відхилено після обговорення» (відхилені записи не видаляються). | H5: Відхилено після обговорення
A6: 2 | B6: №14 BL-60 | C6: Спосіб виправлення нездійсненної вимоги про реєстр НБУ. | D6: Пономаренко Р. В.: вилучити BL-60; у модулі залишити перевірку формату за BL-50, перевірку існування рахунку винести на рівень застосунку. | E6: Городиська А. А.: замінити на перевірку контрольного числа IBAN за математичним алгоритмом без звернення до реєстру. | F6: Обидві позиції прибирають мережеву залежність. Але BL-50 визначає лише формат (UA + 27 цифр); перевірка контрольних цифр — нова поведінка модуля, яка змінює його обсяг і потребує нового коду порушення та погодження замовника. | G6: Вилучити BL-60 (позиція 1). Перевірку контрольних цифр, за потреби, запропонувати замовнику як окрему нову вимогу (проміжний ID, напр. BL-55). | H6: Вирішено
A7: 3 | B7: №16 BL-80 | C7: Вилучити BL-80 чи замінити конкретними правилами. | D7: Городиська А. А.: вилучити, бо стабільність покривають вимоги P та S. | E7: Пономаренко Р. В.: замінити спостережуваними правилами (null-аргументи, округлення HALF_UP, balance() без побічних ефектів). | F7: P та S описують систему в цілому, а не поведінку класу AccountLedger. BL-70 покриває лише суму ≤ 0, тож після вилучення null-аргументи й округлення залишилися б без вимоги та без юніт-тестів. | G7: Замінити (позиція 2). Якщо команда вирішить вилучати — зафіксувати це в журналі змін SRS 1.1. | H7: Вирішено
A8: 4 | B8: №19 S-20 | C8: Критерій якості для S-20. | D8: Мажуга І. К.: Тестопридатність — «100 % захист» неможливо перевірити. | E8: Городиська А. А.: Здійсненність — абсолютну гарантію захисту неможливо надати. | F8: Обидва порушення випливають з одного слова-маркера абсолютної гарантії. Це один дефект, а не два; виправлення в обох авторів збігається за змістом (замінити конкретними механізмами захисту). | G8: Один запис із критерієм «Тестопридатність» і двома авторами; виправлення — з аркуша Мажуги. На виконання нормативу ≥ 2 на критерій рішення не впливає (здійсненність покрито P-10, F-80, BL-60). | H8: Вирішено
A9: 5 | B9: №6 F-110 / BL-30 | C9: Яка межа мінімальної суми кредиту правильна: 500 чи 1 000 грн. | D9: Пономаренко Р. В.: змінити F-110 на «від 1 000 грн» (BL-30 — джерело істини). | E9: Можлива позиція замовника: 500 грн — бізнес-вимога, тоді треба змінювати BL-30 і тести модуля. | F9: BL-30 одночасно задає межі P, n і r, і саме на ньому будуватимуться модульні тести (граничні значення). Але яке значення відповідає намірам банку, може підтвердити лише замовник. | G9: До підтвердження замовником прийняти 1 000 грн (BL-30) і виправити F-110; питання винести в перелік запитань до замовника. | H9: Вирішено
